django_admin_autogen/__init__.py
django_admin_autogen/admin.py
django_admin_autogen-0.3.6.dist-info/METADATA
django_admin_autogen-0.3.6.dist-info/WHEEL
django_admin_autogen-0.3.6.dist-info/top_level.txt
django_admin_autogen-0.3.6.dist-info/RECORD
